econompy/__init__.py
econompy/version.py
econompy/data/__init__.py
econompy/data/simulation.py
econompy-0.1.0.dist-info/LICENSE
econompy-0.1.0.dist-info/METADATA
econompy-0.1.0.dist-info/WHEEL
econompy-0.1.0.dist-info/top_level.txt
econompy-0.1.0.dist-info/RECORD
