Metadata-Version: 2.1
Name: econompy
Version: 0.1.0
Summary: The Python package for econometric analysis.
Author-email: Markus Lill <markus.lill@gmx.de>
License: MIT License
Platform: unix
Platform: linux
Platform: osx
Platform: cygwin
Platform: win32
Classifier: Programming Language :: Python :: 3.12
Classifier: Operating System :: Microsoft :: Windows
Classifier: Operating System :: POSIX :: Linux
Classifier: Operating System :: POSIX
Classifier: Operating System :: Unix
Classifier: Operating System :: MacOS
Requires-Python: >=3.12
License-File: LICENSE
Requires-Dist: pandas >=2.1.2
Provides-Extra: dev
Requires-Dist: black ; extra == 'dev'
Requires-Dist: isort ; extra == 'dev'
Requires-Dist: mypy ; extra == 'dev'
Requires-Dist: pre-commit ; extra == 'dev'
Requires-Dist: ruff ; extra == 'dev'
Provides-Extra: doc
Requires-Dist: mkdocs ; extra == 'doc'
Requires-Dist: mkdocstrings ; extra == 'doc'
Requires-Dist: mkdocstrings[python] ; extra == 'doc'
Requires-Dist: mkdocs-material ; extra == 'doc'
Requires-Dist: Pygments ; extra == 'doc'
Provides-Extra: test
Requires-Dist: pytest ; extra == 'test'
Requires-Dist: pytest-cov ; extra == 'test'
Requires-Dist: codecov ; extra == 'test'
Requires-Dist: pre-commit ; extra == 'test'
